bunnystream/__init__.py
bunnystream/config.py
bunnystream/docs.py
bunnystream/events.py
bunnystream/exceptions.py
bunnystream/logger.py
bunnystream/subscription.py
bunnystream/warren.py
bunnystream-1.0.7.dist-info/licenses/LICENSE
bunnystream-1.0.7.dist-info/METADATA
bunnystream-1.0.7.dist-info/WHEEL
bunnystream-1.0.7.dist-info/top_level.txt
bunnystream-1.0.7.dist-info/RECORD
