Metadata-Version: 2.4
Name: bunnystream
Version: 1.0.7
Summary: Event system that uses RabbitMQ as a message broker.
Author-email: Marc Ford <marc@example.com>
Maintainer-email: Marc Ford <marc@example.com>
License: MIT
Project-URL: Homepage, https://github.com/MarcFord/bunnystream
Project-URL: Bug Reports, https://github.com/MarcFord/bunnystream/issues
Project-URL: Source, https://github.com/MarcFord/bunnystream
Project-URL: Documentation, https://github.com/MarcFord/bunnystream#readme
Project-URL: Changelog, https://github.com/MarcFord/bunnystream/blob/main/CHANGELOG.md
Keywords: rabbitmq,messaging,event-driven,message-broker,amqp
Classifier: Development Status :: 4 - Beta
Classifier: Intended Audience :: Developers
Classifier: Operating System :: OS Independent
Classifier: Programming Language :: Python :: 3
Classifier: Programming Language :: Python :: 3.9
Classifier: Programming Language :: Python :: 3.10
Classifier: Programming Language :: Python :: 3.11
Classifier: Programming Language :: Python :: 3.12
Classifier: Topic :: Software Development :: Libraries :: Python Modules
Classifier: Topic :: System :: Networking
Classifier: Topic :: Communications
Requires-Python: >=3.9
License-File: LICENSE
Requires-Dist: importlib-metadata>=8.7.0
Requires-Dist: pika<7.0,>=1.3.2
Provides-Extra: test
Requires-Dist: pytest>=6.0; python_version >= "3.7" and extra == "test"
Requires-Dist: pytest-cov<4.0,>=2.10; extra == "test"
Requires-Dist: pytest-mock<4.0,>=3.6; extra == "test"
Requires-Dist: responses<1.0,>=0.20; extra == "test"
Requires-Dist: pylint>=3.3.7; extra == "test"
Provides-Extra: dev
Requires-Dist: black>=22.0; extra == "dev"
Requires-Dist: isort>=5.0; extra == "dev"
Requires-Dist: mypy>=1.0; extra == "dev"
Requires-Dist: bandit>=1.7; extra == "dev"
Requires-Dist: flake8>=4.0; extra == "dev"
Requires-Dist: pre-commit>=2.20; extra == "dev"
Dynamic: license-file
